MANIFEST.in
README.md
setup.cfg
setup.py
rbp_setup_tools/.DS_Store
rbp_setup_tools/__init__.py
rbp_setup_tools/code_generation.py
rbp_setup_tools/types.py
rbp_setup_tools/__pycache__/__init__.cpython-36.pyc
rbp_setup_tools/__pycache__/code_generation.cpython-36.pyc
rbp_setup_tools/__pycache__/types.cpython-36.pyc
redblackpy/.DS_Store
redblackpy/__init__.py
redblackpy.egg-info/PKG-INFO
redblackpy.egg-info/SOURCES.txt
redblackpy.egg-info/dependency_links.txt
redblackpy.egg-info/not-zip-safe
redblackpy.egg-info/requires.txt
redblackpy.egg-info/top_level.txt
redblackpy/benchmark/.DS_Store
redblackpy/benchmark/__init__.py
redblackpy/benchmark/timer.cpp
redblackpy/benchmark/timer.pyx
redblackpy/core/.DS_Store
redblackpy/core/exceptions/.DS_Store
redblackpy/core/exceptions/qs_exceptions.hpp
redblackpy/core/timer/timer.hpp
redblackpy/core/tree/.DS_Store
redblackpy/core/tree/rb_node.tpp
redblackpy/core/tree/rb_node_valued.tpp
redblackpy/core/tree/rb_tree.tpp
redblackpy/core/tree/tree.hpp
redblackpy/core/trees_iterator/iterator.hpp
redblackpy/core/trees_iterator/iterator.tpp
redblackpy/cython_source/.DS_Store
redblackpy/cython_source/__arithmetic.pxi
redblackpy/cython_source/__dtype_tree_processing.pxi
redblackpy/cython_source/__interpolation.pxi
redblackpy/cython_source/__tree_series_dtype.pxi
redblackpy/cython_source/arithmetic.pxi
redblackpy/cython_source/base_tree_series.pxi
redblackpy/cython_source/c_pyobject.pxi
redblackpy/cython_source/dtype_tree_processing.pxi
redblackpy/cython_source/interpolation.pxi
redblackpy/cython_source/object_tree_processing.pxi
redblackpy/cython_source/tree_series_dtype.pxi
redblackpy/cython_source/trees_iterator.pxi
redblackpy/series/.DS_Store
redblackpy/series/__init__.py
redblackpy/series/series_iterator.cpp
redblackpy/series/series_iterator.pxd
redblackpy/series/series_iterator.pyx
redblackpy/series/tree_series.cpp
redblackpy/series/tree_series.pxd
redblackpy/series/tree_series.pyx
redblackpy/tree_cython_api/.DS_Store
redblackpy/tree_cython_api/__init__.pxd
redblackpy/tree_cython_api/tree.pxd
redblackpy/tree_cython_api/types_mapping.pxd