Metadata-Version: 1.2
Name: redblackpy
Version: 0.1.3.0
Summary: Data structures based on red-black trees.
Home-page: https://intuitionengineeringteam.github.io/RedBlackPy/
Author: Solodskikh Kirill
Author-email: hypo@intuition.engineering
Maintainer: Intuition
Maintainer-email: dev@intuition.engineering
License: Apache License 2.0
Download-URL: https://github.com/IntuitionEngineeringTeam/RedBlackPy/archive/master.zip
Platform: UNKNOWN
Classifier: Programming Language :: Python :: 2.7
Classifier: Programming Language :: Python :: 3
